ImageStat/__init__.py
ImageEnhance/__init__.py
ImageMath/__init__.py
ImageColor/__init__.py
ImageChops/__init__.py
ImageSequence/__init__.py
ImageDraw/__init__.py
ImageFont/__init__.py
ImagePalette/__init__.py
ImageMorph/__init__.py
Image/__init__.py
ImageFilter/__init__.py
pil_compat-1.0.0.dist-info/top_level.txt
pil_compat-1.0.0.dist-info/DESCRIPTION.rst
pil_compat-1.0.0.dist-info/METADATA
pil_compat-1.0.0.dist-info/RECORD
pil_compat-1.0.0.dist-info/WHEEL
pil_compat-1.0.0.dist-info/metadata.json
ImageOps/__init__.py
ImageFile/__init__.py
ImagePath/__init__.py
