Metadata-Version: 2.0
Name: pil-compat
Version: 1.0.0
Summary: Compatibility modules, bridging PIL -> Pillow
Home-page: http://github.com/prophile/pil-compat
Author: Alistair Lynn
Author-email: alistair@alynn.co.uk
License: UNKNOWN
Platform: UNKNOWN
Classifier: Development Status :: 2 - Pre-Alpha
Classifier: License :: OSI Approved :: MIT License
Classifier: Programming Language :: Python
Classifier: Topic :: Multimedia :: Graphics
Requires-Dist: pillow
